pybuilder_pycharm_workspace/__init__.py
pybuilder_pycharm_workspace/constants.py
pybuilder_pycharm_workspace/errors.py
pybuilder_pycharm_workspace/helpers.py
pybuilder_pycharm_workspace/messages.py
pybuilder_pycharm_workspace/resources/__init__.py
pybuilder_pycharm_workspace/resources/templates.py
pybuilder_pycharm_workspace-0.1.3.dist-info/METADATA
pybuilder_pycharm_workspace-0.1.3.dist-info/WHEEL
pybuilder_pycharm_workspace-0.1.3.dist-info/namespace_packages.txt
pybuilder_pycharm_workspace-0.1.3.dist-info/top_level.txt
pybuilder_pycharm_workspace-0.1.3.dist-info/zip-safe
pybuilder_pycharm_workspace-0.1.3.dist-info/RECORD
