Metadata-Version: 2.1
Name: pybuilder-pycharm-workspace
Version: 0.1.3
Summary: PyBuilder PyCharm Workspaces Plugin
Home-page: https://github.com/yeuk0/pybuilder-pycharm-workspace
Author: Diego BM
Author-email: diegobm92@gmail.com
License: Apache License, Version 2.0
Platform: UNKNOWN
Classifier: Development Status :: 3 - Alpha
Classifier: Programming Language :: Python
